jenkins_external.py
jenkins_external-0.2.dist-info/METADATA
jenkins_external-0.2.dist-info/RECORD
jenkins_external-0.2.dist-info/WHEEL
jenkins_external-0.2.dist-info/entry_points.txt
jenkins_external-0.2.dist-info/top_level.txt
