Metadata-Version: 2.1
Name: jenkins-external
Version: 0.2
Summary: Runs a command, and sends its output to a Jenkins external job.
Home-page: https://github.com/quantum5/jenkins-external
Author: quantum
Author-email: quantum2048@gmail.com
License: MIT
Keywords: jenkins command report
Platform: UNKNOWN
Classifier: Development Status :: 3 - Alpha
Classifier: Environment :: Console
Classifier: Intended Audience :: System Administrators
Classifier: License :: OSI Approved :: MIT License
Classifier: Operating System :: Microsoft :: Windows
Classifier: Operating System :: POSIX
Classifier: Programming Language :: Python
Classifier: Programming Language :: Python :: 2
Classifier: Programming Language :: Python :: 2.7
Classifier: Programming Language :: Python :: 3
Classifier: Programming Language :: Python :: 3.4
Classifier: Programming Language :: Python :: 3.5
Classifier: Programming Language :: Python :: 3.6
Classifier: Programming Language :: Python :: 3.7
Classifier: Topic :: System :: Logging
Classifier: Topic :: System :: Monitoring
